magic/__init__.py
magic/actions.py
magic/lib.py
magic/magic.py
magic/recon.py
magic/requests.py
magic/version.py
pymagico-0.2.dist-info/METADATA
pymagico-0.2.dist-info/WHEEL
pymagico-0.2.dist-info/top_level.txt
pymagico-0.2.dist-info/RECORD
