Metadata-Version: 2.1
Name: pymagico
Version: 0.2
Summary: PyMagic is a pure Python wrapper around libmagic
Home-page: UNKNOWN
Author: Erick Salas
Author-email: erick.salas@ermiry.com
License: UNKNOWN
Platform: UNKNOWN
Classifier: Programming Language :: Python :: 3
Classifier: License :: OSI Approved :: MIT License
Classifier: Operating System :: OS Independent
Requires-Python: >=3.6
